mapmanagercore/.DS_Store
mapmanagercore/__init__.py
mapmanagercore/_version.py
mapmanagercore/analysis_params.py
mapmanagercore/benchmark.py
mapmanagercore/config.py
mapmanagercore/logger.py
mapmanagercore/pyodide_main.py
mapmanagercore/utils.py
mapmanagercore/annotations/.DS_Store
mapmanagercore/annotations/__init__.py
mapmanagercore/annotations/base.py
mapmanagercore/annotations/mutation.py
mapmanagercore/annotations/pyodide.py
mapmanagercore/annotations/single_time_point/__init__.py
mapmanagercore/annotations/single_time_point/base.py
mapmanagercore/annotations/single_time_point/interactions.py
mapmanagercore/annotations/single_time_point/layers.py
mapmanagercore/annotations/single_time_point/segment.py
mapmanagercore/data/__init__.py
mapmanagercore/layers/__init__.py
mapmanagercore/layers/layer.py
mapmanagercore/layers/line.py
mapmanagercore/layers/point.py
mapmanagercore/layers/polygon.py
mapmanagercore/layers/utils.py
mapmanagercore/lazy_geo_pandas/__init__.py
mapmanagercore/lazy_geo_pandas/attributes.py
mapmanagercore/lazy_geo_pandas/lazy.py
mapmanagercore/lazy_geo_pandas/log.py
mapmanagercore/lazy_geo_pandas/schema.py
mapmanagercore/lazy_geo_pandas/utils.py
mapmanagercore/lazy_geo_pd_images/__init__.py
mapmanagercore/lazy_geo_pd_images/image_slices.py
mapmanagercore/lazy_geo_pd_images/metadata.py
mapmanagercore/lazy_geo_pd_images/store.py
mapmanagercore/lazy_geo_pd_images/loader/__init__.py
mapmanagercore/lazy_geo_pd_images/loader/base.py
mapmanagercore/lazy_geo_pd_images/loader/imageio.py
mapmanagercore/lazy_geo_pd_images/loader/zarr.py
mapmanagercore/schemas/__init__.py
mapmanagercore/schemas/segment.py
mapmanagercore/schemas/spine.py
mapmanagercore-0.1.27.post0.dist-info/METADATA
mapmanagercore-0.1.27.post0.dist-info/WHEEL
mapmanagercore-0.1.27.post0.dist-info/top_level.txt
mapmanagercore-0.1.27.post0.dist-info/RECORD
